LICENSE.txt
setup.py
Drkcrw.egg-info/PKG-INFO
Drkcrw.egg-info/SOURCES.txt
Drkcrw.egg-info/dependency_links.txt
Drkcrw.egg-info/not-zip-safe
Drkcrw.egg-info/top_level.txt
code/__init__.py